cigem/__init__.py
cigem/__main__.py
cigem/commands/__init__.py
cigem/commands/main.py
cigem-0.0.0.dist-info/METADATA
cigem-0.0.0.dist-info/WHEEL
cigem-0.0.0.dist-info/entry_points.txt
cigem-0.0.0.dist-info/top_level.txt
cigem-0.0.0.dist-info/RECORD
