Metadata-Version: 2.1
Name: cigem
Version: 0.0.0
Summary: UNKNOWN
Home-page: UNKNOWN
Author: André Bienemann
Author-email: andre.bienemann@gmail.com
License: UNKNOWN
Platform: UNKNOWN
Requires-Dist: click
